[
  {
    "ingredients": [
      "60 ml gin",
      "10 ml dry vermouth"
    ],
    "instructions": "Pour all ingredients into mixing glass with ice cubes. Stir well. Strain into chilled martini cocktail glass.",
    "name": "martini cocktail"
  },
  {
    "ingredients": [
      "Glass of beer",
      "Grenadine (to taste)"
    ],
    "instructions": "Pour grenadine into glass, followed by beer, leaving pink-hued beer head on top",
    "name": "queen mary"
  },
  {
    "ingredients": [
      "1 pint (~16 parts) beer",
      "1 shot (1.5 parts) sake"
    ],
    "instructions": "The shot of sake is dropped into the beer, causing it to fizz violently.  The drink should then be consumed immediately.",
    "name": "sake bomb"
  },
  {
    "ingredients": [
      "3 cl (1 part) Cognac",
      "3 cl (1 part) Creme de cacao (brown)",
      "3 cl (1 part) cream"
    ],
    "instructions": "Shake and strain into a chilled cocktail glass. Sprinkle with fresh ground nutmeg.",
    "name": "brandy alexander"
  },
  {
    "ingredients": [
      "50 ml Rye whiskey",
      "20 ml Sweet red vermouth",
      "1 dash Angostura bitters"
    ],
    "instructions": "Pour all ingredients into mixing glass with ice cubes. Stir well. Strain into a chilled cocktail glass.",
    "name": "brandy manhattan"
  },
  {
    "ingredients": [
      "5 cl (two parts) Cyprus brandy",
      "2.5 cl (one part) lemon squash",
      "2-4 drops of bitters",
      "Top with carbonated water"
    ],
    "instructions": "Stir into glass over ice, garnish and serve.",
    "name": "brandy sour (cyprus)"
  },
  {
    "ingredients": [
      "1 1/2  ounces brandy",
      "3/4  ounce yellow Chartreuse",
      "3/4  ounce lemon juice"
    ],
    "instructions": "Shake with ice in a cocktail shaker, then strain into a chilled Coupe glass and top with a splash of chilled club soda or seltzer.",
    "name": "brandy daisy"
  },
  {
    "ingredients": [
      "Brandy",
      "Triple sec",
      "Bitters",
      "Champagne (optional)"
    ],
    "instructions": "Shake or stir with ice.",
    "name": "chicago cocktail"
  },
  {
    "ingredients": [
      "4 parts applejack",
      "1 part lemon or lime juice",
      "1/2 part grenadine"
    ],
    "instructions": "Traditionally shaken into a chilled glass, garnished, and served straight up.",
    "name": "jack rose"
  },
  {
    "ingredients": [
      "1 part cognac",
      "1 part Benedictine"
    ],
    "instructions": "Combine and stir.",
    "name": "panama"
  },
  {
    "ingredients": [
      "1 oz Brandy",
      "1 oz Benedictine"
    ],
    "instructions": "Server straight up or on ice",
    "name": "b & b"
  },
  {
    "ingredients": [
      "One part hpnotiq",
      "One part cognac"
    ],
    "instructions": "Stir together and serve over ice.",
    "name": "incredible hulk"
  },
  {
    "ingredients": [
      "3 parts Brandy",
      "2 parts Yellow Chartreuse",
      "1 part Lillet",
      "1 part Orange Juice",
      "1 part Dubonnet"
    ],
    "instructions": "Shake ingredients together with ice, and strain into a cocktail glass.",
    "name": "the blenheim"
  },
  {
    "ingredients": [
      "52.5 ml dry gin",
      "22.5 ml lemon juice",
      "22.5 ml orange juice",
      "2 teaspoons honey syrup"
    ],
    "instructions": "Stir honey syrup with lemon and orange juices until it dissolves, add gin and shake with ice. Strain into chilled cocktail glass",
    "name": "bee's knees"
  },
  {
    "ingredients": [
      "1 oz Gin",
      "1 oz Sweet vermouth",
      "1 oz Herbal liqueur, Green Chartreuse",
      "1 ds Orange bitters",
      "1  Maraschino cherry (as garnish)"
    ],
    "instructions": "Stir, strain, straight up, cocktail glass, garnish.",
    "name": "bijou"
  },
  {
    "ingredients": [
      "3 parts Brandy",
      "2 parts Yellow Chartreuse",
      "1 part Lillet",
      "1 part Orange Juice",
      "1 part Dubonnet"
    ],
    "instructions": "Shake ingredients together with ice, and strain into a cocktail glass.",
    "name": "four score"
  },
  {
    "ingredients": [
      "1 1/2 oz Light rum, Plantation 3 Star",
      "3/4 oz Bianco Vermouth, Dolin",
      "1/2 oz Luxardo Bitter",
      "3/4 oz Lime juice",
      "1/2 oz Cane syrup, Petite Canne",
      "5  Grapes (red)",
      "1 spl Overproof rum (for garnish; see instructions)"
    ],
    "instructions": "Muddle, shake, fine strain into a coupe, garnish with a thin orange peel wrapped around another grape, dipped in 151-proof rum, and set aflame, then extinguished in the drink.",
    "name": "french connection"
  },
  {
    "ingredients": [
      "4 cL (1 part) Brandy",
      "12 cL (3 parts) Ginger ale",
      "Dash of Angostura bitter (optional)"
    ],
    "instructions": "Pour brandy and ginger ale directly into highball glass with ice cubes. Stir gently. Garnish with lemon zest. If desired, add dashes of Angostura Bitter.",
    "name": "horse's neck"
  },
  {
    "ingredients": [
      "60 ml Pisco",
      "30 ml lime juice",
      "20 ml simple syrup",
      "1 egg white",
      "Several drops of aromatic bitters at the end"
    ],
    "instructions": "Vigorously shake contents in a cocktail shaker with ice cubes, then strain into a glass and garnish with bitters.[1]",
    "name": "pisco sour"
  },
  {
    "ingredients": [
      "3 parts Brandy",
      "2 parts Yellow Chartreuse",
      "1 part Lillet",
      "1 part Orange Juice",
      "1 part Dubonnet"
    ],
    "instructions": "Shake ingredients together with ice, and strain into a cocktail glass.",
    "name": "savoy corpse reviver"
  },
  {
    "ingredients": [
      "3.5 cl (7 parts) gin",
      "2 cl (4 parts) apricot brandy",
      "1.5 cl (3 parts) orange juice"
    ],
    "instructions": "Shake together over ice.  Strain into cocktail glass and serve chilled.",
    "name": "paradise"
  },
  {
    "ingredients": [
      "5 cl cognac",
      "2 cl triple sec",
      "2 cl lemon juice"
    ],
    "instructions": "Pour all ingredients into cocktail shaker filled with ice. Shake well and strain into cocktail glass.",
    "name": "sidecar"
  },
  {
    "ingredients": [
      "1 oz Gin (London Dry)",
      "1 oz Creme de Cacao",
      "1 oz Cream"
    ],
    "instructions": "Shake with ice and strain into a pre-cooled cocktail glass.",
    "name": "alexander"
  },
  {
    "ingredients": [
      "1 measure gin",
      "1/2 measure sweet vermouth",
      "1/2 measure orange juice",
      "1/4 measure orange curacao or triple sec"
    ],
    "instructions": "Shake with ice and strain into a chilled large cocktail glass",
    "name": "damn the weather"
  },
  {
    "ingredients": [
      "1 oz Bourbon",
      "1/2 oz Sweet vermouth",
      "1/2 oz Curacao",
      "3/4 oz Lime juice",
      "1 lf Mint (as garnish)",
      "1 wdg Lime (as garnish)"
    ],
    "instructions": "Shake, strain, straight up, cocktail glass, garnish",
    "name": "derby"
  },
  {
    "ingredients": [
      "3 oz Port",
      "1 oz Cognac",
      "1 oz Heavy cream",
      "1 t Herbal liqueur, Yellow Chartreuse",
      "1  Whole egg",
      "2 t Sugar",
      "1 pn Nutmeg (Grated)"
    ],
    "instructions": "Mix everything (except Chartreuse & Nutmeg)) with a lot of cracked ice, shake well and strain.  Float the Chartreuse on top with a spoon and add a dusting of the grated nutmeg",
    "name": "porto flip"
  },
  {
    "ingredients": [
      "3 parts Brandy",
      "2 parts Yellow Chartreuse",
      "1 part Lillet",
      "1 part Orange Juice",
      "1 part Dubonnet"
    ],
    "instructions": "Shake ingredients together with ice, and strain into a cocktail glass.",
    "name": "savoy affair"
  },
  {
    "ingredients": [
      "2/3 oz Gin",
      "2/3 oz Calvados",
      "2/3 oz Apricot liqueur"
    ],
    "instructions": "Shake (or stir), strain, up.",
    "name": "angel face"
  },
  {
    "ingredients": [
      "2 oz Gin (or cognac)",
      "1 oz Lemon juice",
      "1 oz Simple syrup",
      "3 oz Sparkling white wine (Brut, chilled)",
      "1 twst Lemon zest"
    ],
    "instructions": "Shake all but wine, strain into ice-filled highball glass, top with chilled wine.",
    "name": "french 75"
  },
  {
    "ingredients": [
      "3 parts Brandy",
      "2 parts Yellow Chartreuse",
      "1 part Lillet",
      "1 part Orange Juice",
      "1 part Dubonnet"
    ],
    "instructions": "Shake ingredients together with ice, and strain into a cocktail glass.",
    "name": "my fair lady"
  },
  {
    "ingredients": [
      "4 oz Ginger beer",
      "1/2 oz Lime juice",
      "1/4 oz Demerara syrup",
      "1 oz Gin",
      "1 oz Brandy",
      "2 ds Bitters, Angostura"
    ],
    "instructions": "Glassware: Collins or highballGarnish: Mint spring and swizzle stickPour ginger beer into glass. Shake remaining ingredients with cracked or cubed ice in shaker. Strain contents into glass, fill with more ice, and garnish.",
    "name": "suffering bastard"
  },
  {
    "ingredients": [
      "3 parts Brandy",
      "2 parts Yellow Chartreuse",
      "1 part Lillet",
      "1 part Orange Juice",
      "1 part Dubonnet"
    ],
    "instructions": "Shake ingredients together with ice, and strain into a cocktail glass.",
    "name": "wolfram"
  },
  {
    "ingredients": [
      "1 pint (~13 parts) beer",
      "3 parts Amaretto",
      "1 part high-proof liquor"
    ],
    "instructions": "Layer the two spirits in the shot glass, with the high-proof liquor on top.  Light the shot and allow it to burn; then extinguish it by dropping it into the beer glass. Drink immediately.",
    "name": "flaming doctor pepper"
  },
  {
    "ingredients": [
      "3 cl gin",
      "1.5 cl cherry liqueur (such as maraschino)",
      "0.75 cl Cointreau",
      "0.75 cl DOM Benedictine",
      "1 cl Grenadine",
      "12 cl pineapple juice",
      "1.5 cl fresh lime juice",
      "1 dash Angostura bitters"
    ],
    "instructions": "Pour all ingredients into cocktail shaker filled with ice cubes. Shake well. Strain into highball glass. Garnish with pineapple and cocktail cherry.",
    "name": "singapore sling"
  },
  {
    "ingredients": [
      "50 ml cognac",
      "20 ml white creme de menthe"
    ],
    "instructions": "Pour all ingredients into mixing glass with ice cubes. Stir well. Strain into chilled martini cocktail glass.",
    "name": "stinger"
  },
  {
    "ingredients": [
      "6 cl (2 ounces) (6 parts) gin",
      "1 cl (0.33 ounce) (1 part) dry vermouth"
    ],
    "instructions": "\nStir well in a shaker with ice, then strain into a chilled martini glass. Garnish and serve\n",
    "name": "gibson"
  },
  {
    "ingredients": [
      "2 oz Gin, Tanqueray",
      "2/3 oz Lime cordial, Rose's"
    ],
    "instructions": "Stir & strain into a chilled glass",
    "name": "gimlet"
  },
  {
    "ingredients": [
      "5 cl (1 parts) gin",
      "20 cl (4 parts) Grapefruit juice"
    ],
    "instructions": "Shake gin and grapefruit juice in cocktail shaker. Strain into a highball glass.",
    "name": "greyhound"
  },
  {
    "ingredients": [
      "15 ml Tequila",
      "15 ml Vodka",
      "15 ml White rum",
      "15 ml Cointreau",
      "15 ml Gin",
      "30 ml Lemon juice",
      "20 ml simple syrup",
      "Top with Cola"
    ],
    "instructions": "Add all ingredients into highball glass filled with ice. Stir gently. Optionally garnish with lemon slice.[1]",
    "name": "long island iced tea"
  },
  {
    "ingredients": [
      "1 1/2 oz Gin",
      "1 1/2 oz Orange juice",
      "1 t Absinthe",
      "1 t Raspberry syrup (or grenadine)"
    ],
    "instructions": "Shake, strain, straight up, cocktail glass",
    "name": "monkey gland"
  },
  {
    "ingredients": [
      "3 cl gin",
      "3 cl sweet red vermouth",
      "3 cl Campari"
    ],
    "instructions": "Stir into glass over ice, garnish and serve.",
    "name": "negroni"
  },
  {
    "ingredients": [
      "60 ml cachaca",
      "1 lime cut into small wedges",
      "4 teaspoons white cane sugar"
    ],
    "instructions": "Place lime and sugar into a double old fashioned glass and muddle gently. Fill the glass with cracked ice and add Cachaça. Stir gently to involve ingredients.",
    "name": "caipirinha"
  },
  {
    "ingredients": [
      "4.5 cl Gin",
      "2 cl Kina Lillet",
      "1.5 cl light creme de cacao",
      "2cl fresh lemon juice"
    ],
    "instructions": "Shake in an iced cocktail shaker, and strain into a cocktail glass. Garnish with a lemon twist.",
    "name": "20th century"
  },
  {
    "ingredients": [
      "2 oz sloe gin",
      "1 oz dry vermouth",
      "dash Angostura bitters",
      "dash Absinthe",
      "2 oz Irish whiskey",
      "1 oz. sweet vermouth",
      "dash Angostura bitters",
      "dash Absinthe"
    ],
    "instructions": "Fill mixing glass with gin, vermouth, and bitters. Add ice and stir until chilled, then add strain into a chilled glass. Garnish with a lemon peel.[1]",
    "name": "blackthorn"
  },
  {
    "ingredients": [
      "2 oz Genever",
      "1/2  Lemon (About 3/4 oz of juice)",
      "1/4 oz Simple syrup (or powdered sugar)",
      "4 oz Soda water"
    ],
    "instructions": "Shake all but soda water, strain over ice in a Collins, top with soda. Alternately, build in glass and give a quick stir.",
    "name": "john collins"
  },
  {
    "ingredients": [
      "15ml of white rum",
      "5ml Malibu",
      "5ml lime juice",
      "Mint leaves",
      "1 sprig of mint"
    ],
    "instructions": "In a shaker add white rum, Malibu, lime juice, some mint leaves and crushed ice, garnish with the sprig of mint.",
    "name": "cojito"
  },
  {
    "ingredients": [
      "4 wdg Lime (1/2 lime)",
      "1 spg Mint",
      "2 oz Light rum",
      "1 oz Simple syrup (or 2 tsp sugar)",
      "2 oz Club soda (to top)",
      "1 spg Mint (as garnish)"
    ],
    "instructions": "Muddle lime wedges. Muddle mint lightly. Add ice, syrup, rum. Shake, fine strain into glass with more ice. Top with club soda, garnish with additional lime wedge and mint sprig.",
    "name": "mojito"
  },
  {
    "ingredients": [
      "4.5 cL (3 parts) Old Tom Gin",
      "3 cL (2 parts) freshly squeezed lemon juice",
      "1.5 cL (1 part) sugar syrup",
      "6 cL (4 parts) carbonated water to taste"
    ],
    "instructions": "Mix the gin, lemon juice and sugar syrup in a tall glass with ice, top up with soda water, garnish and serve.",
    "name": "juan collins"
  },
  {
    "ingredients": [
      "45 ml white rum",
      "20 ml fresh lime juice",
      "6 sprigs of mint",
      "2 teaspoons white cane sugar (or 2 cl of sugar syrup)",
      "Soda water"
    ],
    "instructions": "Muddle mint leaves with sugar and lime juice. Add a splash of soda water and fill the glass with cracked ice. Pour the rum and top with soda water. Light stir to involve all ingredients. Garnish with sprig of mint leaves and lime slice.",
    "name": "mojito blanco"
  },
  {
    "ingredients": [
      "1 part Jack Daniel's Tennessee whiskey",
      "3-5 parts Coca-Cola (strength dependent)",
      "Ice"
    ],
    "instructions": "Pour Jack Daniel's brand Tennessee whiskey into a Collins glass filled with ice. Fill to desired level with Coca-Cola. Stir lightly.",
    "name": "jack and coke"
  },
  {
    "ingredients": [
      "6 cL Bourbon whiskey",
      "4 mint leaves",
      "1 teaspoon powdered sugar",
      "2 teaspoons water"
    ],
    "instructions": "In a highball glass gently muddle the mint, sugar and water. Fill the glass with cracked ice, add Bourbon and stir well until the glass is well frosted. Garnish with a mint sprig.",
    "name": "mint julep"
  },
  {
    "ingredients": [
      "1/4 t Sugar",
      "1/2 oz Lime juice",
      "1/2 oz Allspice Dram, St Elizabeth",
      "1 1/4 oz Dark rum"
    ],
    "instructions": "Stir the sugar into the lime in a cocktail shaker. Add other ingredients and shake with ice. Strain into a cocktail glass.",
    "name": "jasper's jamaican"
  },
  {
    "ingredients": [
      "4.5cl Gin",
      "1.5cl lemon juice",
      "1.5cl raspberry syrup",
      "0.5cl Dry Vermouth",
      "1 egg white or 20 ml aquafaba or 4 drops cocktail foamer"
    ],
    "instructions": "Dry shake ingredients to emulsify, add ice, shake and served straight up.",
    "name": "clover club cocktail"
  },
  {
    "ingredients": [
      "1 oz. Gin",
      ".5 oz. Dry vermouth",
      ".5 oz. Sweet vermouth",
      "Mint sprig"
    ],
    "instructions": "Shake with ice and strain into chilled cocktail glass, add mint.",
    "name": "cooperstown cocktail"
  },
  {
    "ingredients": [
      "60 ml gin",
      "10 ml dry vermouth"
    ],
    "instructions": "Pour all ingredients into mixing glass with ice cubes. Stir well. Strain into chilled martini cocktail glass.",
    "name": "martini"
  },
  {
    "ingredients": [
      "2oz bourbon, rye whiskey, or gin",
      "Half of a lime squeezed and dropped in the glass",
      "Sparkling mineral water"
    ],
    "instructions": "Combine spirit, lime and shell in a highball or wine glass. Add ice, stir and then add sparkling mineral water.",
    "name": "lime rickey"
  },
  {
    "ingredients": [
      "3/4 oz Gin",
      "3/4 oz Triple sec, Cointreau",
      "3/4 oz Aromatized wine, Lillet Blanc",
      "3/4 oz Lemon juice",
      "1 rinse Absinthe"
    ],
    "instructions": "Shake, strain, straight up, cocktail glass rinsed with absinthe",
    "name": "corpse reviver #2"
  },
  {
    "ingredients": [
      "6 parts Gin",
      "3 parts Sweet Red Vermouth",
      "3 parts Dry Vermouth",
      "4 parts Pineapple juice"
    ],
    "instructions": "Shake all ingredients in an ice-filled cocktail shaker. Strain into chilled martini or cocktail glass.",
    "name": "queens"
  },
  {
    "ingredients": [
      "6 cl white rum",
      "2 cl lime juice",
      "2 bar spoons superfine sugar"
    ],
    "instructions": "In a cocktail shaker add all ingredients. Stir well to dissolve the sugar. Add ice and shake. Strain into chilled cocktail glass.",
    "name": "daiquiri"
  },
  {
    "ingredients": [
      "One part tequila",
      "One part 7 Up, ginger ale, Sprite, or Mountain Dew"
    ],
    "instructions": "Mix carefully to avoid releasing the dissolved CO2.",
    "name": "tequila slammer"
  },
  {
    "ingredients": [
      "4.5 cl (3 parts) tequila",
      "9 cl (6 parts) orange juice",
      "1.5 cl (1 part) grenadine syrup"
    ],
    "instructions": "Pour the tequila and orange juice into glass over ice.  Add the grenadine, which will sink to the bottom.  Stir gently to create the sunrise effect.  Garnish and serve.",
    "name": "tequila sunrise"
  },
  {
    "ingredients": [
      "4.5 cl (3 parts) tequila",
      "9 cl (6 parts) orange juice",
      "1.5 cl (1 part) grenadine syrup"
    ],
    "instructions": "Pour the tequila and orange juice into glass over ice.  Add the grenadine, which will sink to the bottom.  Stir gently to create the sunrise effect.  Garnish and serve.",
    "name": "tequila sunset"
  },
  {
    "ingredients": [
      "one part Midori liqueur",
      "one part Kahlua",
      "one part Baileys Irish Cream"
    ],
    "instructions": "\nPour Kahlua into shot glass\nLayer Midori on top.\nCarefully add Baileys, letting it float on top to finish.\n",
    "name": "quick fuck"
  },
  {
    "ingredients": [
      "1 oz Batavia Arrack, Van Oosten",
      "1 oz Trinidad rum, Scarlet Ibis",
      "1 oz Lime cordial (Toby Cecchini's; see link)",
      "3 lf Curry (shaken)",
      "1 wdg Lime (as garnish)"
    ],
    "instructions": "Shake, strain over cracked ice, garnish.",
    "name": "javanese daiquiri"
  },
  {
    "ingredients": [
      "33 4/5 oz Spiced Rum, Sailor Jerry",
      "11 3/10 oz Pineapple juice",
      "11 3/10 oz Lemon juice",
      "11 3/10 oz Ginger liqueur, Domaine de Canton",
      "5 7/12 oz Demerara syrup",
      "1/2 oz Bitters (Smeby's Buddah's Hand Lemon and Kaffir Lime)",
      "1/2 oz Lemon bitters, Bitter Truth"
    ],
    "instructions": "Add everything to a large punchbowl, float decorative block ice.",
    "name": "pacquiao's punch"
  },
  {
    "ingredients": [
      "1 1/2 oz Mezcal",
      "3/4 oz Sweet vermouth, Carpano Punt e Mes",
      "1/2 oz Coffee liqueur, Galliano Ristretto",
      "1 ds Chocolate bitters"
    ],
    "instructions": "Stir, strain into old fashioned glass with a large cube or sphere. No garnish.",
    "name": "five point palm exploding heart technique"
  },
  {
    "ingredients": [
      "45 ml gin",
      "15 ml lemon juice",
      "15 ml maraschino liqueur",
      "1 barspoon creme de violette"
    ],
    "instructions": "Add all ingredients into cocktail shaker filled with ice. Shake well and strain into cocktail glass. Garnish with a cherry.",
    "name": "aviation"
  },
  {
    "ingredients": [
      "1 1/2 ounces gin[1]",
      "3/4 ounce orange curacao",
      "1 teaspoon lime juice",
      "Dash bitters",
      "Dash orange bitters"
    ],
    "instructions": "Shake ingredients together in a mixer with cubed ice. Strain into chilled glass, garnish and serve.",
    "name": "pegu"
  },
  {
    "ingredients": [
      "3 parts Brandy",
      "2 parts Yellow Chartreuse",
      "1 part Lillet",
      "1 part Orange Juice",
      "1 part Dubonnet"
    ],
    "instructions": "Shake ingredients together with ice, and strain into a cocktail glass.",
    "name": "royal arrival"
  },
  {
    "ingredients": [
      "1 1/2 ounces gin",
      "1/2 ounce Maraschino liqueur",
      "1/8 ounce Parfait d'Amour liqueur",
      "1/3 ounce lemon juice"
    ],
    "instructions": "Add all ingredients into cocktail shaker filled with ice. Shake well and strain into cocktail glass. Garnish with a lemon peel.",
    "name": "takumi's aviation"
  },
  {
    "ingredients": [
      "45 ml gin",
      "15 ml vodka",
      "7.5 ml Lillet Blanc"
    ],
    "instructions": "Pour all ingredients into a cocktail shaker filled with ice cubes. Shake and strain into a chilled cocktail glass.",
    "name": "vesper martini"
  },
  {
    "ingredients": [
      "1 US fluid ounce (30 ml) light rum",
      "1 oz. brandy",
      "1 oz. overproof rum",
      "4 US fluid ounces (120 ml) orange juice",
      "2 US fluid ounces (60 ml) lemon juice, unsweetened",
      "2 oz. orgeat syrup"
    ],
    "instructions": "Combine ingredients except overproof rum with 2 scoops of crushed ice in a blender. Pour, and place small amount of overproof rum into volcano and carefully light.",
    "name": "flaming volcano"
  },
  {
    "ingredients": [
      "1 part cognac",
      "1 part Benedictine"
    ],
    "instructions": "Combine and stir.",
    "name": "brave bull"
  },
  {
    "ingredients": [
      "22.5ml gin",
      "22.5ml lime juice",
      "22.5ml green Chartreuse",
      "22.5ml maraschino liqueur"
    ],
    "instructions": "Shake with ice and strain into a cocktail glass.",
    "name": "the last word"
  },
  {
    "ingredients": [
      "4 cl gin",
      "3 cl  Triple Sec",
      "2 cl lemon juice"
    ],
    "instructions": "Add all ingredients into cocktail shaker filled with ice. Shake well and strain into large cocktail glass.",
    "name": "white lady"
  },
  {
    "ingredients": [
      "3 cl white rum",
      "3 cl cognac",
      "3 cl triple sec",
      "2 cl fresh lemon juice"
    ],
    "instructions": "Pour all ingredients into shaker with ice cubes, shake, strain into chilled cocktail glass.",
    "name": "between the sheets"
  },
  {
    "ingredients": [
      "2 cl light rum",
      "2 cl vodka",
      "1.5 cl  Blue Curacao",
      "9 cl pineapple juice, unsweetened",
      "3 cl Sour mix"
    ],
    "instructions": "Combine all ingredients with ice, stir or shake, then pour into a hurricane glass with the ice. For garnish score pineapple or orange slice with a knife and insert onto rim of glass; optionally use toothpick or cocktail umbrella to spear maraschino cherry through center and attach to top of fruit slice; otherwise float cherry on top of ice!",
    "name": "blue hawaii"
  },
  {
    "ingredients": [
      "1 ounce Dark Rum",
      "1 ounce Kahlua",
      "1 ounce Dark Creme de Cacao",
      "2 ounces Cream of Coconut",
      "2 ounces Milk or Half & Half",
      "1 cup ice"
    ],
    "instructions": "Blend all the ingredients together in a blender, including the ice, and then strain into a hurricane glass. Place cherry on top of the drink as a garnish and serve. Whipped cream can also be added as a garnish to the top of the drink before the cherry.[1]",
    "name": "bushwacker"
  },
  {
    "ingredients": [
      "4oz. black rum",
      "4oz. gold rum",
      "Juice of 2 lemons",
      "5oz. pineapple juice",
      "5oz orange juice",
      "2oz. Bermuda falernum",
      "6 dashes Angostura Bitters"
    ],
    "instructions": "Mix in pitcher with crushed ice, shake vigorously until a frothing head appears. Strain into cocktail glasses. Garnish with a slice of orange and a cherry. Serves 6.",
    "name": "rum swizzle"
  },
  {
    "ingredients": [
      "3 cl white rum",
      "1.5 cl Galliano",
      "1.5 cl triple sec",
      "1.5 cl lime juice"
    ],
    "instructions": "Pour all ingredients into a cocktail shaker, shake well with ice, strain into chilled cocktail glass",
    "name": "yellow bird"
  },
  {
    "ingredients": [
      "3 cl (6 parts) Gin",
      "1.5 cl (3 parts) Sweet Red Vermouth",
      "1 cl (2 parts) Dry Vermouth",
      "1.5 cl (3 parts) Orange juice"
    ],
    "instructions": "Pour into cocktail shaker all ingredients with ice cubes, shake well. Strain in chilled cocktail or martini glass.",
    "name": "bronx"
  },
  {
    "ingredients": [
      "2 oz Gin",
      "1 oz Fino sherry",
      "1 ds Orange bitters",
      "1 twst Lemon peel"
    ],
    "instructions": "Stir, strain, up, twist.",
    "name": "tuxedo"
  },
  {
    "ingredients": [
      "4 cl Vodka",
      "2 cl Peach schnapps",
      "4 cl Orange juice",
      "4 cl cranberry juice"
    ],
    "instructions": "Build all ingredients in a highball glass filled with ice. Garnish with orange slice.",
    "name": "sex on the beach"
  },
  {
    "ingredients": [
      "3 parts Brandy",
      "2 parts Yellow Chartreuse",
      "1 part Lillet",
      "1 part Orange Juice",
      "1 part Dubonnet"
    ],
    "instructions": "Shake ingredients together with ice, and strain into a cocktail glass.",
    "name": "nixon"
  },
  {
    "ingredients": [
      "30 ml rye whiskey",
      "30 ml cognac",
      "30 ml sweet vermouth",
      "1 bar spoon Benedictine",
      "2 dashes Peychaud's bitters"
    ],
    "instructions": "Pour all ingredients into mixing glass with ice cubes. Stir well. Strain into a chilled cocktail glass.",
    "name": "vieux carré"
  },
  {
    "ingredients": [
      "One part red wine",
      "One part cola or another carbonated soft drink"
    ],
    "instructions": "Stir together over plenty of ice.",
    "name": "kalimotxo"
  },
  {
    "ingredients": [
      "2 oz Gin, Plymouth",
      "3/4 oz Dry vermouth",
      "1/2 oz Herbal liqueur, Green Chartreuse",
      "1 t Maraschino Liqueur",
      "1 ds Celery bitters, Bittermens Orchard Street Celery Shrub",
      "1 twst Lemon peel"
    ],
    "instructions": "Stir with ice, strain and garnish with a lemon twist.",
    "name": "oxford comma"
  },
  {
    "ingredients": [
      "3 oz Rye",
      "1/2 oz Simple syrup (or up to 3/4 oz to taste)",
      "5 ds Peychaud's Bitters (to taste)",
      "1 rinse Absinthe",
      "1 twst Lemon zest (as garnish)"
    ],
    "instructions": "Pack lowball glass with cracked ice. In a second lowball or mixing glass, stir ingredient with ice, empty serving glass and rinse with Absinthe, strain and serve without ice. May also be served in a flute or cocktail glass",
    "name": "sazerac"
  },
  {
    "ingredients": [
      "1 1/2 oz Old Tom Gin",
      "1 1/2 oz Sweet vermouth",
      "1/4 oz Maraschino Liqueur",
      "2 ds Bitters, Boker's (or angostura)",
      "1 twst Orange peel (as garnish)"
    ],
    "instructions": "Stir, strain, cocktail, orange twist",
    "name": "martinez"
  },
  {
    "ingredients": [
      "2.5 cl (one part) Cyprus ouzo",
      "7.5 cl (three parts) fresh orange juice",
      "2.5 cl (one part) fresh lemon juice",
      "2-4 drops of bitters"
    ],
    "instructions": "Shake ouzo and fresh juices vigorously together, coat the rim of a glass with powdered sugar and pour drink into glass over ice, and add dash of bitters. Garnish with a thin orange slice and serve.",
    "name": "ouzini"
  },
  {
    "ingredients": [
      "45 ml Jamaican dark rum",
      "45 ml Puerto Rican gold rum",
      "30 ml Demerara rum",
      "20 ml fresh lime juice",
      "15 ml falernum",
      "15 ml Donn's Mix (2 parts fresh yellow grapefruit and 1 part cinnamon syrup)",
      "1 tsp Grenadine syrup",
      "1 dash Angostura bitters",
      "6 drops Pernod"
    ],
    "instructions": "Mix ingredients in a shaker with crushed ice. Pour into a tall tumbler glass.",
    "name": "zombie"
  },
  {
    "ingredients": [
      "4.5 cl (3 parts) vodka",
      "9 cl (6 parts) Tomato juice",
      "1.5 cl (1 part) Lemon juice",
      "2 to 3 dashes of Worcestershire Sauce",
      "Tabasco sauce",
      "Celery salt",
      "Black pepper"
    ],
    "instructions": "Stirring gently, pour all ingredients into highball glass. Garnish.",
    "name": "ginza mary"
  },
  {
    "ingredients": [
      "One raw egg (or egg yolk only)",
      "3/4 cup (200 cc) sake",
      "Honey or sugar to taste"
    ],
    "instructions": "Whisk the raw egg yolk and honey/sugar into 3/4 cup hot sake (hot enough to lightly cook the egg – 1:30 in the microwave).",
    "name": "tamagozake"
  },
  {
    "ingredients": [
      "4.5 cl (3 parts) tequila",
      "9 cl (6 parts) orange juice",
      "1.5 cl (1 part) grenadine syrup"
    ],
    "instructions": "Pour the tequila and orange juice into glass over ice.  Add the grenadine, which will sink to the bottom.  Stir gently to create the sunrise effect.  Garnish and serve.",
    "name": "arizona biltmore"
  },
  {
    "ingredients": [
      "1 part cognac",
      "1 part Benedictine"
    ],
    "instructions": "Combine and stir.",
    "name": "bloody aztec"
  },
  {
    "ingredients": [
      "1 shot Apple Vodka",
      "1/2 cup Apple Juice",
      "1/2 cup Lemonade"
    ],
    "instructions": "Combine all three ingredients into a chilled glass and serve with ice and garnish.",
    "name": "fizzy apple cocktail"
  }
]